deezspot/__init__.py
deezspot/__taggers__.py
deezspot/easy_spoty.py
deezspot/exceptions.py
deezspot/deezloader/__download__.py
deezspot/deezloader/__download_utils__.py
deezspot/deezloader/__init__.py
deezspot/deezloader/__utils__.py
deezspot/deezloader/dee_api.py
deezspot/deezloader/deegw_api.py
deezspot/deezloader/deezer_settings.py
deezspot/libutils/__init__.py
deezspot/libutils/others_settings.py
deezspot/libutils/utils.py
deezspot/models/__init__.py
deezspot/models/album.py
deezspot/models/episode.py
deezspot/models/playlist.py
deezspot/models/preferences.py
deezspot/models/smart.py
deezspot/models/track.py
deezspot/spotloader/__download__.py
deezspot/spotloader/__init__.py
deezspot/spotloader/__spo_api__.py
deezspot/spotloader/spotify_settings.py
deezspot-2025.1.8.dist-info/LICENSE
deezspot-2025.1.8.dist-info/METADATA
deezspot-2025.1.8.dist-info/WHEEL
deezspot-2025.1.8.dist-info/top_level.txt
deezspot-2025.1.8.dist-info/RECORD
