Metadata-Version: 2.1
Name: deezspot
Version: 2025.1.8
Summary: Downloads songs, albums, episode or playlists from deezer and spotify with this packages! (clone from https://pypi.org/project/deezloader/)
Home-page: https://github.com/farihdzkyy/deezspot
Author: farihdzakyy
Author-email: farihdzakyy <farihmuhammad75@gmail.com>
License: GNU Affero General Public License v3
Project-URL: Homepage, https://github.com/farihdzkyy/deezspot
Project-URL: Repository, https://github.com/farihdzkyy/deezspot.git
Project-URL: Documentation, https://github.com/farihdzkyy/deezspot/blob/main/README.md
Requires-Python: >=3.10
License-File: LICENSE
Requires-Dist: mutagen
Requires-Dist: pycryptodome
Requires-Dist: requests
Requires-Dist: spotipy
Requires-Dist: tqdm
Requires-Dist: fastapi
Requires-Dist: uvicorn[standard]
Requires-Dist: spotipy-anon
Requires-Dist: librespot
